tzgeo/__init__.py
tzgeo/__main__.py
tzgeo/db.py
tzgeo/tzgeo.sqlite
tzgeo-0.0.4.dist-info/DESCRIPTION.rst
tzgeo-0.0.4.dist-info/METADATA
tzgeo-0.0.4.dist-info/RECORD
tzgeo-0.0.4.dist-info/WHEEL
tzgeo-0.0.4.dist-info/metadata.json
tzgeo-0.0.4.dist-info/top_level.txt
