Metadata-Version: 2.0
Name: tzgeo
Version: 0.0.4
Summary: Get the timezone for a location
Home-page: https://github.com/judy2k/tzgeo
Author: Mark Smith
Author-email: mark.smith@practicalpoetry.co.uk
License: MIT License
Platform: UNKNOWN
Classifier: Development Status :: 4 - Beta
Classifier: Environment :: Console
Classifier: Intended Audience :: Developers
Classifier: License :: OSI Approved :: MIT License
Classifier: Operating System :: OS Independent
Classifier: Programming Language :: Python
Classifier: Topic :: Database
Classifier: Topic :: Scientific/Engineering :: GIS
Classifier: Topic :: Software Development :: Libraries :: Python Modules
Requires-Dist: pyspatialite (>=3.0.1-alpha-0)
